xontrib/pygitstatus/__init__.py
xontrib/pygitstatus/entrypoint.py
xontrib/pygitstatus/event_hooks.py
xontrib/pygitstatus/prompts.py
xontrib_pygitstatus-0.1.0.dist-info/LICENSE
xontrib_pygitstatus-0.1.0.dist-info/METADATA
xontrib_pygitstatus-0.1.0.dist-info/WHEEL
xontrib_pygitstatus-0.1.0.dist-info/entry_points.txt
xontrib_pygitstatus-0.1.0.dist-info/top_level.txt
xontrib_pygitstatus-0.1.0.dist-info/RECORD
