Metadata-Version: 2.1
Name: xontrib-pygitstatus
Version: 0.1.0
Summary: PyGit implementation of xonsh's builtin gitstatus PROMPT
Author-email: Kyle Gottfried <Kyle.Gottfried@outlook.com>
License:                    GNU LESSER GENERAL PUBLIC LICENSE
Project-URL: Homepage, https://github.com/Spitfire1900/xontrib-pygitstatus
Project-URL: Documentation, https://github.com/Spitfire1900/xontrib-pygitstatus/blob/main/README.md
Project-URL: Code, https://github.com/Spitfire1900/xontrib-pygitstatus
Project-URL: Issues, https://github.com/Spitfire1900/xontrib-pygitstatus/issues
Platform: any
Classifier: Programming Language :: Python :: 3 :: Only
Classifier: Programming Language :: Python :: 3.10
Classifier: Programming Language :: Python :: 3.11
Classifier: Programming Language :: Python :: 3.12
Classifier: Programming Language :: Python :: 3.13
Classifier: License :: OSI Approved :: GNU Lesser General Public License v3 (LGPLv3)
Classifier: Operating System :: OS Independent
Classifier: Topic :: System :: Shells
Classifier: Topic :: System :: System Shells
Classifier: Topic :: Terminals
Requires-Python: >=3.10
License-File: LICENSE
Requires-Dist: xonsh>=0.12.5
Requires-Dist: pygit2>=1.11.1
Provides-Extra: dev
Requires-Dist: build>=1.2.2; extra == "dev"
Requires-Dist: pytest>=7.0; extra == "dev"
Requires-Dist: gitpython>=3.1.43; extra == "dev"
